optimization_algorithms/__init__.py
optimization_algorithms/algorithm/__init__.py
optimization_algorithms/algorithm/algorithm.py
optimization_algorithms/algorithm/exact/__init__.py
optimization_algorithms/algorithm/metaheuristic/__init__.py
optimization_algorithms/algorithm/metaheuristic/electro_magnetism_like_metaheusristic/__init__.py
optimization_algorithms/algorithm/metaheuristic/genetic_algorithm/__init__.py
optimization_algorithms/algorithm/metaheuristic/metaheuristic.py
optimization_algorithms/algorithm/metaheuristic/solution_code_distance_cache_control_statistics.py
optimization_algorithms/algorithm/metaheuristic/variable_neighborhood_search/__init__.py
optimization_algorithms/algorithm/metaheuristic/variable_neighborhood_search/vns_optimizer.py
optimization_algorithms/algorithm/metaheuristic/variable_neighborhood_search/vns_support_for_target_solution.py
optimization_algorithms/algorithm/output_control.py
optimization_algorithms/target_problem/__init__.py
optimization_algorithms/target_problem/target_problem.py
optimization_algorithms/target_solution/__init__.py
optimization_algorithms/target_solution/evaluation_cache_control_statistics.py
optimization_algorithms/target_solution/target_solution.py
optimization_algorithms/utils/__init__.py
optimization_algorithms/utils/files.py
optimization_algorithms/utils/logger.py
optimization_algorithms_library-0.1.0.dist-info/LICENSE
optimization_algorithms_library-0.1.0.dist-info/METADATA
optimization_algorithms_library-0.1.0.dist-info/WHEEL
optimization_algorithms_library-0.1.0.dist-info/RECORD
