Metadata-Version: 2.1
Name: optimization-algorithms-library
Version: 0.1.0
Summary: Library with optimization algorithms
License: Apache
Author: Vladimir Filipovic
Author-email: vladofilipovic@hotmail.com
Requires-Python: >=3.11,<4.0
Classifier: License :: Other/Proprietary License
Classifier: Programming Language :: Python :: 3
Classifier: Programming Language :: Python :: 3.11
Requires-Dist: sphinx (>=7.2.4,<8.0.0)
Requires-Dist: sphinx-copybutton (>=0.5.2,<0.6.0)
Requires-Dist: sphinx-rtd-theme (>=1.3.0,<2.0.0)
